{
  "track.fallen_down": {
    "replace": true,
    "sounds": [
      {
        "name": "locusazzurro_icaruswings:track_fallen_down",
        "stream": true
      }
    ]
  },
  "track.ring_my_bell": {
    "replace": true,
    "sounds": [
      {
        "name": "locusazzurro_icaruswings:track_ring_my_bell",
        "stream": true
      }
    ]
  },
  "item.spear.throw": {
    "subtitle": "subtitles.item.spear.throw",
    "replace": true,
    "sounds": [
      "locusazzurro_icaruswings:spear_throw_1",
      "locusazzurro_icaruswings:spear_throw_2",
      "locusazzurro_icaruswings:spear_throw_3"
    ]
  },
  "item.spear.hit": {
    "subtitle": "subtitles.item.spear.hit",
    "replace": true,
    "sounds": [
      "minecraft:item/trident/pierce1",
      "minecraft:item/trident/pierce2",
      "minecraft:item/trident/pierce3"
    ]
  },
  "item.spear.hit_ground": {
    "subtitle": "subtitles.item.spear.hit_ground",
    "replace": true,
    "sounds": [
      {
        "name": "locusazzurro_icaruswings:spear_impact_1",
        "volume": 0.9
      },
      {
        "name": "locusazzurro_icaruswings:spear_impact_2",
        "volume": 0.9
      },
      {
        "name": "locusazzurro_icaruswings:spear_impact_3",
        "volume": 0.9
      },
      {
        "name": "locusazzurro_icaruswings:spear_impact_4",
        "volume": 0.9
      }
    ]
  },
  "item.air_jar.fill": {
    "subtitle": "subtitles.item.air_jar.fill",
    "replace": true,
    "sounds": [
      "item/bottle/fill_dragonbreath1",
      "item/bottle/fill_dragonbreath2"
    ]
  },
  "item.air_jar.empty": {
    "subtitle": "subtitles.item.air_jar.empty",
    "replace": true,
    "sounds": [
      "mob/chicken/plop"
    ]
  },
  "item.wind_wand.burst": {
    "subtitle": "subtitles.item.wind_wand.burst",
    "replace": true,
    "sounds": [
      "mob/ghast/fireball4"
    ]
  },
  "entity.artemis_missile.launch": {
    "subtitle": "subtitles.entity.artemis_missile.launch",
    "replace": true,
    "sounds": [
      "locusazzurro_icaruswings:artemis_missile_launch_1",
      "locusazzurro_icaruswings:artemis_missile_launch_2",
      "locusazzurro_icaruswings:artemis_missile_launch_3"
    ]
  },
  "entity.time_rift.collapse": {
    "subtitle": "subtitles.entity.time_rift.collapse",
    "replace": true,
    "sounds": [
      {
        "name": "locusazzurro_icaruswings:time_rift_collapse",
        "stream": true
      }
    ]
  },
  "item.time_rift_generator.fire": {
    "subtitle": "subtitles.item.time_rift_generator.fire",
    "replace": true,
    "sounds": [
        "locusazzurro_icaruswings:time_rift_generator_fire"
    ]
  },
  "item.transport_card.activation.generic": {
    "subtitle": "subtitles.item.transport_card.activation",
    "replace": true,
    "sounds": [
      "locusazzurro_icaruswings:transport_card_activation_generic"
    ]
  },
  "item.transport_card.activation.artemis": {
    "subtitle": "subtitles.item.transport_card.activation",
    "replace": true,
    "sounds": [
      "locusazzurro_icaruswings:transport_card_activation_artemis"
    ]
  },
  "item.transport_card.activation.electronic": {
    "subtitle": "subtitles.item.transport_card.activation",
    "replace": true,
    "sounds": [
      "locusazzurro_icaruswings:transport_card_activation_electronic"
    ]
  },
  "item.transport_card.activation.chrono": {
    "subtitle": "subtitles.item.transport_card.activation",
    "replace": true,
    "sounds": [
      "locusazzurro_icaruswings:transport_card_activation_chrono"
    ]
  },
  "item.transport_card.teleport_anchor": {
    "subtitle": "subtitles.item.transport_card.teleport_anchor",
    "replace": true,
    "sounds": [
      "block/respawn_anchor/charge1",
      "block/respawn_anchor/charge2",
      "block/respawn_anchor/charge3"
    ]
  },
  "item.transport_card.teleport": {
    "subtitle": "subtitles.iitem.transport_card.teleport",
    "replace": true,
    "sounds": [
      "mob/endermen/portal",
      "mob/endermen/portal2"
    ]
  },
  "item.transport_card.activation.fail": {
    "subtitle": "subtitles.item.transport_card.fail",
    "replace": true,
    "sounds": [
      "random/fizz"
    ]
  }
}