{
  "type": "minecraft:crafting_shaped",
  "category": "equipment",
  "key": {
    "1": "locusazzurro_icaruswings:restored_fallen_relic_defensive",
    "2": "locusazzurro_icaruswings:restored_fallen_relic_defensive",
    "3": "locusazzurro_icaruswings:restored_fallen_relic_offensive",
    "4": "locusazzurro_icaruswings:restored_fallen_relic_interface",
    "A": "locusazzurro_icaruswings:synapse_alloy_ingot",
    "C": "locusazzurro_icaruswings:upgraded_fallen_relic_core",
    "E": "minecraft:elytra",
    "R": "locusazzurro_icaruswings:synapse_wings_recharger"
  },
  "pattern": [
    "ACA",
    "1E2",
    "3R4"
  ],
  "result": {
    "id": "locusazzurro_icaruswings:hiyori_wings"
  }
}